autosphinx/__init__.py
autosphinx/conf.py
autosphinx-1.0a2.dist-info/METADATA
autosphinx-1.0a2.dist-info/WHEEL
autosphinx-1.0a2.dist-info/top_level.txt
autosphinx-1.0a2.dist-info/RECORD
