Metadata-Version: 2.1
Name: autosphinx
Version: 1.0a2
Summary: Easy packaging for cython wheels.
Home-page: https://github.com/JeanMaximilienCadic/autosphinx-python
Author: Jean Maximilien Cadic
Author-email: j.cadic@9dw-lab.com
License: UNKNOWN
Platform: UNKNOWN
Classifier: Programming Language :: Python :: 3.5
Classifier: License :: OSI Approved :: MIT License
Classifier: Operating System :: OS Independent
Requires-Python: >=3.6
Requires-Dist: sphinx-rtd-theme
Requires-Dist: gnutools-python
